abstract_logins/__init__.py
abstract_logins/abstract_logins_flask.py
abstract_logins/app/__init__.py
abstract_logins/app/endpoints/__init__.py
abstract_logins/app/endpoints/imports.py
abstract_logins/app/endpoints/views.py
abstract_logins/app/endpoints/files/__init__.py
abstract_logins/app/endpoints/files/imports.py
abstract_logins/app/endpoints/files/routes/__init__.py
abstract_logins/app/endpoints/files/routes/secure_delete.py
abstract_logins/app/endpoints/files/routes/secure_downloads.py
abstract_logins/app/endpoints/files/routes/secure_env.py
abstract_logins/app/endpoints/files/routes/secure_files.py
abstract_logins/app/endpoints/files/routes/secure_register.py
abstract_logins/app/endpoints/files/routes/secure_uploads.py
abstract_logins/app/endpoints/settings/__init__.py
abstract_logins/app/endpoints/settings/imports.py
abstract_logins/app/endpoints/settings/routes/__init__.py
abstract_logins/app/endpoints/settings/routes/get_endpoints.py
abstract_logins/app/endpoints/settings/routes/secure_settings.py
abstract_logins/app/endpoints/settings/routes/testfuncs.py
abstract_logins/app/endpoints/users/__init__.py
abstract_logins/app/endpoints/users/imports.py
abstract_logins/app/endpoints/users/routes/__init__.py
abstract_logins/app/endpoints/users/routes/change_password.py
abstract_logins/app/endpoints/users/routes/secure_login.py
abstract_logins/app/endpoints/users/routes/secure_logout.py
abstract_logins/app/endpoints/users/routes/secure_users.py
abstract_logins/app/imports/__init__.py
abstract_logins/app/imports/flask_utils.py
abstract_logins/app/imports/secure_utils.py
abstract_logins/app/imports/src/__init__.py
abstract_logins/app/imports/src/constants.py
abstract_logins/app/imports/src/file_items.py
abstract_logins/app/imports/src/imports.py
abstract_logins/app/imports/src/nufunctions.py
abstract_logins/app/imports/src/secure_utils.py
abstract_logins/app/imports/src/user_dirs.py
abstract_logins/app/imports/src/auth_utils/__init__.py
abstract_logins-0.0.0.38.dist-info/METADATA
abstract_logins-0.0.0.38.dist-info/WHEEL
abstract_logins-0.0.0.38.dist-info/top_level.txt
abstract_logins-0.0.0.38.dist-info/RECORD
